ridehail/__init__.py
ridehail/__main__.py
ridehail/animation_legacy.py
ridehail/atom.py
ridehail/config.py
ridehail/convergence.py
ridehail/dispatch.py
ridehail/export_keyboard_mappings.py
ridehail/keyboard_mappings.py
ridehail/sequence.py
ridehail/simulation.py
ridehail/simulation_results.py
ridehail/simulation_runner.py
ridehail/animation/__init__.py
ridehail/animation/base.py
ridehail/animation/matplotlib.py
ridehail/animation/sequence_animation.py
ridehail/animation/terminal_base.py
ridehail/animation/terminal_console.py
ridehail/animation/terminal_map.py
ridehail/animation/terminal_sequence.py
ridehail/animation/terminal_stats.py
ridehail/animation/text.py
ridehail/animation/utils.py
ridehail/animation/web_browser.py
ridehail/lab/app.js
ridehail/lab/experiment-tab.js
ridehail/lab/favicon.png
ridehail/lab/index.html
ridehail/lab/style.css
ridehail/lab/webworker.js
ridehail/lab/whatif-tab.js
ridehail/lab/worker.py
ridehail/lab/components/experiment-tab.html
ridehail/lab/components/game-tab.html
ridehail/lab/components/whatif-tab.html
ridehail/lab/dist/manifest.json
ridehail/lab/dist/ridehail-2025.11.10.1-py3-none-any.whl
ridehail/lab/js/app-state.js
ridehail/lab/js/config-file.js
ridehail/lab/js/config-mapping.js
ridehail/lab/js/config.js
ridehail/lab/js/constants.js
ridehail/lab/js/dom-elements.js
ridehail/lab/js/fullscreen.js
ridehail/lab/js/input-handlers.js
ridehail/lab/js/keyboard-handler.js
ridehail/lab/js/keyboard-mappings.json
ridehail/lab/js/loading-tips.js
ridehail/lab/js/message-handler.js
ridehail/lab/js/scale-inference.js
ridehail/lab/js/session-storage.js
ridehail/lab/js/sim-settings.js
ridehail/lab/js/toast.js
ridehail/lab/js/vehicle-count-monitor.js
ridehail/lab/modules/map.js
ridehail/lab/modules/stats.js
ridehail/lab/modules/whatif.js
ridehail/lab/tests/test-baseline-data.js
ridehail/lab/tests/test-config-file.html
ridehail/lab/tests/test-labsimsettings-migration.js
ridehail/lab/tests/test-phase1.html
ridehail-2025.11.10.1.dist-info/licenses/LICENSE
ridehail-2025.11.10.1.dist-info/METADATA
ridehail-2025.11.10.1.dist-info/WHEEL
ridehail-2025.11.10.1.dist-info/entry_points.txt
ridehail-2025.11.10.1.dist-info/top_level.txt
ridehail-2025.11.10.1.dist-info/RECORD
