Metadata-Version: 2.4
Name: ridehail
Version: 2025.11.10.1
Summary: Simulations of ridehail traffic and trips
Home-page: https://github.com/tomslee/ridehail-animation
Author: Tom Slee
Author-email: tom@tomslee.net
License-Expression: MIT
Project-URL: Homepage, https://tomslee.github.io/ridehail/
Project-URL: Documentation, https://tomslee.github.io/ridehail/
Project-URL: Repository, https://github.com/tomslee/ridehail
Project-URL: Issues, https://github.com/tomslee/ridehail/issues
Project-URL: Live Demo, https://tomslee.github.io/ridehail/lab/
Keywords: simulation,ridehail,rideshare,transportation,traffic,mobility,ride-hailing,urban-planning
Classifier: Development Status :: 4 - Beta
Classifier: Intended Audience :: Science/Research
Classifier: Intended Audience :: Developers
Classifier: Programming Language :: Python :: 3
Classifier: Programming Language :: Python :: 3.12
Classifier: Topic :: Scientific/Engineering :: Visualization
Classifier: Topic :: Scientific/Engineering
Classifier: Operating System :: OS Independent
Requires-Python: >=3.12
License-File: LICENSE
Requires-Dist: numpy>=2.1.1
Requires-Dist: textual>=0.79.1
Requires-Dist: textual-plotext>=0.2.1
Requires-Dist: plotext>=5.3.2
Requires-Dist: rich>=13.8.1
Provides-Extra: desktop
Requires-Dist: matplotlib>=3.9.2; extra == "desktop"
Requires-Dist: seaborn>=0.13.2; extra == "desktop"
Requires-Dist: scipy>=1.14.1; extra == "desktop"
Requires-Dist: pandas>=2.3.3; extra == "desktop"
Provides-Extra: dev
Requires-Dist: textual-dev>=1.6.1; extra == "dev"
Requires-Dist: ruff>=0.13.2; extra == "dev"
Requires-Dist: pytest>=8.4.2; extra == "dev"
Requires-Dist: psutil>=7.1.0; extra == "dev"
Provides-Extra: packaging
Requires-Dist: pyapp>=4.16.1; extra == "packaging"
Provides-Extra: full
Requires-Dist: ridehail[desktop,dev,packaging]; extra == "full"
Dynamic: license-file
